partis_basis-0.0.6.data/purelib/partis/basis/__main__.py
partis_basis-0.0.6.dist-info/METADATA
partis_basis-0.0.6.dist-info/LICENSE.txt
partis_basis-0.0.6.dist-info/top_level.txt
partis_basis-0.0.6.dist-info/entry_points.txt
partis_basis-0.0.6.dist-info/WHEEL
partis_basis-0.0.6.dist-info/RECORD
