Metadata-Version: 2.1
Name: partis-basis
Version: 0.0.6
Requires-Python: >=3.7.2
Author: Nanohmics Inc
Summary: 
License-File: LICENSE.txt
